mypythonlib/__init__.py
mypythonlib/myfunctions.py
mypythonlib_aco1_/__init__.py
mypythonlib_aco1_/myfunctions.py
mypythonlibaco1/__init__.py
mypythonlibaco1/myfunctions.py
mypythonlibaco1-0.1.4.dist-info/METADATA
mypythonlibaco1-0.1.4.dist-info/WHEEL
mypythonlibaco1-0.1.4.dist-info/top_level.txt
mypythonlibaco1-0.1.4.dist-info/RECORD
