Metadata-Version: 2.1
Name: mypythonlibaco1
Version: 0.1.4
Summary: My first Custom Python library.
Home-page: https://github.com/albertcdc/my_custom_codes
Author: aco
